LICENSE
MANIFEST.in
README.md
setup.py
django_shawty.egg-info/PKG-INFO
django_shawty.egg-info/SOURCES.txt
django_shawty.egg-info/dependency_links.txt
django_shawty.egg-info/not-zip-safe
django_shawty.egg-info/requires.txt
django_shawty.egg-info/top_level.txt
shawty/__init__.py
shawty/__init__.pyc
shawty/admin.py
shawty/models.py
shawty/models.pyc
shawty/tests.py
shawty/tests.pyc
shawty/migrations/0001_initial.py
shawty/migrations/0001_initial.pyc
shawty/migrations/__init__.py
shawty/migrations/__init__.pyc