Metadata-Version: 1.1
Name: django-shawty
Version: 0.0.3
Summary: Shawty URL shortener server integration for Django.
Home-page: https://github.com/Unified/django_shawty
Author: John Nadratowski
Author-email: john@unifiedsocial.com
License: UNKNOWN
Platform: UNKNOWN
Classifier: Framework :: Django
Classifier: Intended Audience :: Developers
Classifier: Intended Audience :: System Administrators
Classifier: Operating System :: OS Independent
Classifier: Topic :: Software Development
